{
	"configurations" : 
	[
		{
			"directories" : 
			[
				{
					"build" : ".",
					"childIndexes" : 
					[
						1,
						2,
						3,
						4,
						5
					],
					"hasInstallRule" : true,
					"jsonFile" : "directory-.-Debug-1206765c6624e76534f0.json",
					"minimumCMakeVersion" : 
					{
						"string" : "3.21"
					},
					"projectIndex" : 0,
					"source" : ".",
					"targetIndexes" : 
					[
						0,
						1,
						2,
						3,
						4,
						5,
						6,
						7,
						8,
						9,
						10,
						11,
						12,
						13,
						14,
						15,
						16,
						17,
						18,
						19,
						20,
						21,
						22,
						23,
						24,
						25,
						26,
						27
					]
				},
				{
					"build" : "src/libutil",
					"hasInstallRule" : true,
					"jsonFile" : "directory-src.libutil-Debug-86045935720f3df5de01.json",
					"minimumCMakeVersion" : 
					{
						"string" : "3.21"
					},
					"parentIndex" : 0,
					"projectIndex" : 0,
					"source" : "src/libutil"
				},
				{
					"build" : "src/libmath",
					"hasInstallRule" : true,
					"jsonFile" : "directory-src.libmath-Debug-4731921ff0248343c31b.json",
					"minimumCMakeVersion" : 
					{
						"string" : "3.21"
					},
					"parentIndex" : 0,
					"projectIndex" : 0,
					"source" : "src/libmath",
					"targetIndexes" : 
					[
						33
					]
				},
				{
					"build" : "src/app/hello",
					"hasInstallRule" : true,
					"jsonFile" : "directory-src.app.hello-Debug-f8a782bfeed0ac8812e0.json",
					"minimumCMakeVersion" : 
					{
						"string" : "3.21"
					},
					"parentIndex" : 0,
					"projectIndex" : 0,
					"source" : "src/app/hello",
					"targetIndexes" : 
					[
						32
					]
				},
				{
					"build" : "src/app/viewer",
					"hasInstallRule" : true,
					"jsonFile" : "directory-src.app.viewer-Debug-29c9a624708ed77fdc2e.json",
					"minimumCMakeVersion" : 
					{
						"string" : "3.21"
					},
					"parentIndex" : 0,
					"projectIndex" : 0,
					"source" : "src/app/viewer",
					"targetIndexes" : 
					[
						35
					]
				},
				{
					"build" : "tests",
					"childIndexes" : 
					[
						6
					],
					"hasInstallRule" : true,
					"jsonFile" : "directory-tests-Debug-70e4927a02b591d5c1f8.json",
					"minimumCMakeVersion" : 
					{
						"string" : "3.21"
					},
					"parentIndex" : 0,
					"projectIndex" : 0,
					"source" : "tests",
					"targetIndexes" : 
					[
						34
					]
				},
				{
					"build" : "_deps/googletest-build",
					"childIndexes" : 
					[
						7
					],
					"hasInstallRule" : true,
					"jsonFile" : "directory-_deps.googletest-build-Debug-9da9378ab6ba69101747.json",
					"minimumCMakeVersion" : 
					{
						"string" : "3.13"
					},
					"parentIndex" : 5,
					"projectIndex" : 1,
					"source" : "build/ucrt64-debug/_deps/googletest-src"
				},
				{
					"build" : "_deps/googletest-build/googlemock",
					"childIndexes" : 
					[
						8
					],
					"hasInstallRule" : true,
					"jsonFile" : "directory-_deps.googletest-build.googlemock-Debug-8a6d64b8a9e7860f6d81.json",
					"minimumCMakeVersion" : 
					{
						"string" : "3.13"
					},
					"parentIndex" : 6,
					"projectIndex" : 2,
					"source" : "build/ucrt64-debug/_deps/googletest-src/googlemock",
					"targetIndexes" : 
					[
						28,
						29
					]
				},
				{
					"build" : "_deps/googletest-build/googletest",
					"hasInstallRule" : true,
					"jsonFile" : "directory-_deps.googletest-build.googletest-Debug-0cf46e196ac0b0453bd5.json",
					"minimumCMakeVersion" : 
					{
						"string" : "3.13"
					},
					"parentIndex" : 7,
					"projectIndex" : 3,
					"source" : "build/ucrt64-debug/_deps/googletest-src/googletest",
					"targetIndexes" : 
					[
						30,
						31
					]
				}
			],
			"name" : "Debug",
			"projects" : 
			[
				{
					"childIndexes" : 
					[
						1
					],
					"directoryIndexes" : 
					[
						0,
						1,
						2,
						3,
						4,
						5
					],
					"name" : "Aphelion3D",
					"targetIndexes" : 
					[
						0,
						1,
						2,
						3,
						4,
						5,
						6,
						7,
						8,
						9,
						10,
						11,
						12,
						13,
						14,
						15,
						16,
						17,
						18,
						19,
						20,
						21,
						22,
						23,
						24,
						25,
						26,
						27,
						32,
						33,
						34,
						35
					]
				},
				{
					"childIndexes" : 
					[
						2
					],
					"directoryIndexes" : 
					[
						6
					],
					"name" : "googletest-distribution",
					"parentIndex" : 0
				},
				{
					"childIndexes" : 
					[
						3
					],
					"directoryIndexes" : 
					[
						7
					],
					"name" : "gmock",
					"parentIndex" : 1,
					"targetIndexes" : 
					[
						28,
						29
					]
				},
				{
					"directoryIndexes" : 
					[
						8
					],
					"name" : "gtest",
					"parentIndex" : 2,
					"targetIndexes" : 
					[
						30,
						31
					]
				}
			],
			"targets" : 
			[
				{
					"directoryIndex" : 0,
					"id" : "Continuous::@6890427a1f51a3e7e1df",
					"jsonFile" : "target-Continuous-Debug-d6d48d73985c4e9f9934.json",
					"name" : "Continuous",
					"projectIndex" : 0
				},
				{
					"directoryIndex" : 0,
					"id" : "ContinuousBuild::@6890427a1f51a3e7e1df",
					"jsonFile" : "target-ContinuousBuild-Debug-ef1106442775c183a705.json",
					"name" : "ContinuousBuild",
					"projectIndex" : 0
				},
				{
					"directoryIndex" : 0,
					"id" : "ContinuousConfigure::@6890427a1f51a3e7e1df",
					"jsonFile" : "target-ContinuousConfigure-Debug-d44b93c195a8e53b1470.json",
					"name" : "ContinuousConfigure",
					"projectIndex" : 0
				},
				{
					"directoryIndex" : 0,
					"id" : "ContinuousCoverage::@6890427a1f51a3e7e1df",
					"jsonFile" : "target-ContinuousCoverage-Debug-bf3484f6d640d1653ba5.json",
					"name" : "ContinuousCoverage",
					"projectIndex" : 0
				},
				{
					"directoryIndex" : 0,
					"id" : "ContinuousMemCheck::@6890427a1f51a3e7e1df",
					"jsonFile" : "target-ContinuousMemCheck-Debug-b357a05fa4df113db096.json",
					"name" : "ContinuousMemCheck",
					"projectIndex" : 0
				},
				{
					"directoryIndex" : 0,
					"id" : "ContinuousStart::@6890427a1f51a3e7e1df",
					"jsonFile" : "target-ContinuousStart-Debug-05e228b35d7315018c58.json",
					"name" : "ContinuousStart",
					"projectIndex" : 0
				},
				{
					"directoryIndex" : 0,
					"id" : "ContinuousSubmit::@6890427a1f51a3e7e1df",
					"jsonFile" : "target-ContinuousSubmit-Debug-5f249732366fd6416540.json",
					"name" : "ContinuousSubmit",
					"projectIndex" : 0
				},
				{
					"directoryIndex" : 0,
					"id" : "ContinuousTest::@6890427a1f51a3e7e1df",
					"jsonFile" : "target-ContinuousTest-Debug-08929f23d7c479d5b93b.json",
					"name" : "ContinuousTest",
					"projectIndex" : 0
				},
				{
					"directoryIndex" : 0,
					"id" : "ContinuousUpdate::@6890427a1f51a3e7e1df",
					"jsonFile" : "target-ContinuousUpdate-Debug-c6505f63afad5ec94a4c.json",
					"name" : "ContinuousUpdate",
					"projectIndex" : 0
				},
				{
					"directoryIndex" : 0,
					"id" : "Experimental::@6890427a1f51a3e7e1df",
					"jsonFile" : "target-Experimental-Debug-afc34a085bb5e613466c.json",
					"name" : "Experimental",
					"projectIndex" : 0
				},
				{
					"directoryIndex" : 0,
					"id" : "ExperimentalBuild::@6890427a1f51a3e7e1df",
					"jsonFile" : "target-ExperimentalBuild-Debug-c4af6081e6b58f38f729.json",
					"name" : "ExperimentalBuild",
					"projectIndex" : 0
				},
				{
					"directoryIndex" : 0,
					"id" : "ExperimentalConfigure::@6890427a1f51a3e7e1df",
					"jsonFile" : "target-ExperimentalConfigure-Debug-b52b93dbed1ad15829f0.json",
					"name" : "ExperimentalConfigure",
					"projectIndex" : 0
				},
				{
					"directoryIndex" : 0,
					"id" : "ExperimentalCoverage::@6890427a1f51a3e7e1df",
					"jsonFile" : "target-ExperimentalCoverage-Debug-1674032192b387580f27.json",
					"name" : "ExperimentalCoverage",
					"projectIndex" : 0
				},
				{
					"directoryIndex" : 0,
					"id" : "ExperimentalMemCheck::@6890427a1f51a3e7e1df",
					"jsonFile" : "target-ExperimentalMemCheck-Debug-8c30caca9974872faa77.json",
					"name" : "ExperimentalMemCheck",
					"projectIndex" : 0
				},
				{
					"directoryIndex" : 0,
					"id" : "ExperimentalStart::@6890427a1f51a3e7e1df",
					"jsonFile" : "target-ExperimentalStart-Debug-fc9d1b5ad6fa5eb63eee.json",
					"name" : "ExperimentalStart",
					"projectIndex" : 0
				},
				{
					"directoryIndex" : 0,
					"id" : "ExperimentalSubmit::@6890427a1f51a3e7e1df",
					"jsonFile" : "target-ExperimentalSubmit-Debug-d633f97c7bb97fc1f73b.json",
					"name" : "ExperimentalSubmit",
					"projectIndex" : 0
				},
				{
					"directoryIndex" : 0,
					"id" : "ExperimentalTest::@6890427a1f51a3e7e1df",
					"jsonFile" : "target-ExperimentalTest-Debug-60cff82d3ba2f29fa041.json",
					"name" : "ExperimentalTest",
					"projectIndex" : 0
				},
				{
					"directoryIndex" : 0,
					"id" : "ExperimentalUpdate::@6890427a1f51a3e7e1df",
					"jsonFile" : "target-ExperimentalUpdate-Debug-692c3ae19964e37c66ec.json",
					"name" : "ExperimentalUpdate",
					"projectIndex" : 0
				},
				{
					"directoryIndex" : 0,
					"id" : "Nightly::@6890427a1f51a3e7e1df",
					"jsonFile" : "target-Nightly-Debug-d1632e755ba507f476c3.json",
					"name" : "Nightly",
					"projectIndex" : 0
				},
				{
					"directoryIndex" : 0,
					"id" : "NightlyBuild::@6890427a1f51a3e7e1df",
					"jsonFile" : "target-NightlyBuild-Debug-fd249024a4e8a723f848.json",
					"name" : "NightlyBuild",
					"projectIndex" : 0
				},
				{
					"directoryIndex" : 0,
					"id" : "NightlyConfigure::@6890427a1f51a3e7e1df",
					"jsonFile" : "target-NightlyConfigure-Debug-8cc1fa3361b20ca79622.json",
					"name" : "NightlyConfigure",
					"projectIndex" : 0
				},
				{
					"directoryIndex" : 0,
					"id" : "NightlyCoverage::@6890427a1f51a3e7e1df",
					"jsonFile" : "target-NightlyCoverage-Debug-0629efe7c918c76ddb34.json",
					"name" : "NightlyCoverage",
					"projectIndex" : 0
				},
				{
					"directoryIndex" : 0,
					"id" : "NightlyMemCheck::@6890427a1f51a3e7e1df",
					"jsonFile" : "target-NightlyMemCheck-Debug-dc210171e97ebb0a6091.json",
					"name" : "NightlyMemCheck",
					"projectIndex" : 0
				},
				{
					"directoryIndex" : 0,
					"id" : "NightlyMemoryCheck::@6890427a1f51a3e7e1df",
					"jsonFile" : "target-NightlyMemoryCheck-Debug-f5b53726d4d1520d9c43.json",
					"name" : "NightlyMemoryCheck",
					"projectIndex" : 0
				},
				{
					"directoryIndex" : 0,
					"id" : "NightlyStart::@6890427a1f51a3e7e1df",
					"jsonFile" : "target-NightlyStart-Debug-820f985d0c3715a4a805.json",
					"name" : "NightlyStart",
					"projectIndex" : 0
				},
				{
					"directoryIndex" : 0,
					"id" : "NightlySubmit::@6890427a1f51a3e7e1df",
					"jsonFile" : "target-NightlySubmit-Debug-c536f3bd24ee913e56ba.json",
					"name" : "NightlySubmit",
					"projectIndex" : 0
				},
				{
					"directoryIndex" : 0,
					"id" : "NightlyTest::@6890427a1f51a3e7e1df",
					"jsonFile" : "target-NightlyTest-Debug-b1c22f827e9a362ad04a.json",
					"name" : "NightlyTest",
					"projectIndex" : 0
				},
				{
					"directoryIndex" : 0,
					"id" : "NightlyUpdate::@6890427a1f51a3e7e1df",
					"jsonFile" : "target-NightlyUpdate-Debug-b1b8fa394938512fc1d1.json",
					"name" : "NightlyUpdate",
					"projectIndex" : 0
				},
				{
					"directoryIndex" : 7,
					"id" : "gmock::@0f7bb11d64f3678238c7",
					"jsonFile" : "target-gmock-Debug-939a0c9620a28e92a2a6.json",
					"name" : "gmock",
					"projectIndex" : 2
				},
				{
					"directoryIndex" : 7,
					"id" : "gmock_main::@0f7bb11d64f3678238c7",
					"jsonFile" : "target-gmock_main-Debug-eef690317ab107476fb9.json",
					"name" : "gmock_main",
					"projectIndex" : 2
				},
				{
					"directoryIndex" : 8,
					"id" : "gtest::@1ea2dfc0605fe3ab2a3f",
					"jsonFile" : "target-gtest-Debug-960e59ebbf619294f1ce.json",
					"name" : "gtest",
					"projectIndex" : 3
				},
				{
					"directoryIndex" : 8,
					"id" : "gtest_main::@1ea2dfc0605fe3ab2a3f",
					"jsonFile" : "target-gtest_main-Debug-d9e0fd2181ec5f55adf4.json",
					"name" : "gtest_main",
					"projectIndex" : 3
				},
				{
					"directoryIndex" : 3,
					"id" : "hello::@8c6ecfe551c66b4c494e",
					"jsonFile" : "target-hello-Debug-f537245a73002b8e78e8.json",
					"name" : "hello",
					"projectIndex" : 0
				},
				{
					"directoryIndex" : 2,
					"id" : "libmath::@2563312467537a111115",
					"jsonFile" : "target-libmath-Debug-f3591c208fe9dfc44308.json",
					"name" : "libmath",
					"projectIndex" : 0
				},
				{
					"directoryIndex" : 5,
					"id" : "math_tests::@a44f0ac069e85531cdee",
					"jsonFile" : "target-math_tests-Debug-5462acfc04ca679f6d88.json",
					"name" : "math_tests",
					"projectIndex" : 0
				},
				{
					"directoryIndex" : 4,
					"id" : "viewer::@6d966fb3d198aab44a11",
					"jsonFile" : "target-viewer-Debug-243e92aea3f088813587.json",
					"name" : "viewer",
					"projectIndex" : 0
				}
			]
		}
	],
	"kind" : "codemodel",
	"paths" : 
	{
		"build" : "D:/AphelionWorld/Dev/aphelion3d/build/ucrt64-debug",
		"source" : "D:/AphelionWorld/Dev/aphelion3d"
	},
	"version" : 
	{
		"major" : 2,
		"minor" : 8
	}
}
